{"failedItems":[],"newItems":["todos/タブ押下後_チェックリスト.png","todos/タブ押下後_リンク.png"],"deletedItems":[],"passedItems":["components/todo-list/1つ.png","components/todo-list/1つもない.png","components/todo-list/2つ.png","components/todo-list/タブ押下後.png","components/todo-list/マージンチェック.png","components/todo-list/長い文字.png","styles/color/色.png","styles/spacing/余白.png","styles/typography/その他(ラベルや短文など).png","styles/typography/段落.png","styles/typography/見出し.png","styles/typography/重要.png","todos/1つ.png","todos/1つもない.png","todos/2つ.png","todos/タブ押下後.png","todos/長い文字.png"],"expectedItems":["components/todo-list/1つ.png","components/todo-list/1つもない.png","components/todo-list/2つ.png","components/todo-list/タブ押下後.png","components/todo-list/マージンチェック.png","components/todo-list/長い文字.png","styles/color/色.png","styles/spacing/余白.png","styles/typography/その他(ラベルや短文など).png","styles/typography/段落.png","styles/typography/見出し.png","styles/typography/重要.png","todos/1つ.png","todos/1つもない.png","todos/2つ.png","todos/タブ押下後.png","todos/長い文字.png"],"actualItems":["components/todo-list/1つ.png","components/todo-list/1つもない.png","components/todo-list/2つ.png","components/todo-list/タブ押下後.png","components/todo-list/マージンチェック.png","components/todo-list/長い文字.png","styles/color/色.png","styles/spacing/余白.png","styles/typography/その他(ラベルや短文など).png","styles/typography/段落.png","styles/typography/見出し.png","styles/typography/重要.png","todos/1つ.png","todos/1つもない.png","todos/2つ.png","todos/タブ押下後_チェックリスト.png","todos/タブ押下後_リンク.png","todos/タブ押下後.png","todos/長い文字.png"],"diffItems":[],"actualDir":"./actual","expectedDir":"./expected","diffDir":"./diff"}